fincy/__init__.py
fincy/core/__init__.py
fincy/core/base.py
fincy/core/interest.py
fincy/errors/__init__.py
fincy/errors/errors.py
fincy-0.0.1.dev1.dist-info/licenses/LICENSE
fincy-0.0.1.dev1.dist-info/METADATA
fincy-0.0.1.dev1.dist-info/WHEEL
fincy-0.0.1.dev1.dist-info/top_level.txt
fincy-0.0.1.dev1.dist-info/RECORD
