Metadata-Version: 2.4
Name: fincy
Version: 0.0.1.dev1
Summary: A lightweight and extensible Python toolkit for calculating financial metrics.
Author-email: "Debmalya Pramanik (ZenithClown)" <dpramanik.official@gmail.com>
License: MIT License
Project-URL: homepage, https://github.com/finofunda/
Project-URL: sourcecode, https://github.com/finofunda/fincy/
Project-URL: issues, https://github.com/finofunda/fincy/issues/
Project-URL: changelog, https://github.com/finofunda/fincy/blob/master/CHANGELOG.md/
Classifier: Development Status :: 1 - Planning
Classifier: License :: OSI Approved :: MIT License
Classifier: Operating System :: OS Independent
Classifier: Programming Language :: Python :: 3
Classifier: Programming Language :: Python :: 3.11
Classifier: Programming Language :: Python :: 3.12
Requires-Python: >=3.11
License-File: LICENSE
Dynamic: license-file
